imgtoch/__init__.py
imgtoch/__utils__.py
imgtoch-0.2.3.dist-info/LICENSE
imgtoch-0.2.3.dist-info/METADATA
imgtoch-0.2.3.dist-info/WHEEL
imgtoch-0.2.3.dist-info/top_level.txt
imgtoch-0.2.3.dist-info/RECORD
