Metadata-Version: 2.1
Name: imgtoch
Version: 0.2.3
Summary: 一个帮你将图片转为字符图片的模块。
Home-page: https://gitee.com/hrpzcf/imgtoch
Author: hrpzcf
Author-email: hrpzcf@foxmail.com
Maintainer: hrpzcf
Maintainer-email: hrpzcf@foxmail.com
License: MIT License
Keywords: character picture,character image,picture,image
Platform: UNKNOWN
Classifier: Intended Audience :: Developers
Classifier: Development Status :: 4 - Beta
Classifier: License :: OSI Approved :: MIT License
Classifier: Programming Language :: Python :: 3.7
Classifier: Programming Language :: Python :: 3.8
Classifier: Programming Language :: Python :: 3.9
Requires-Python: >=3.7
License-File: LICENSE
Requires-Dist: Pillow
